{
  "outlook": "bullish",
  "predictions": {
    "7_days": {
      "total_jobs": 1015,
      "change_percent": 0.6
    },
    "30_days": {
      "total_jobs": 1035,
      "change_percent": 2.6
    }
  },
  "growing_categories": [
    "Software Engineering",
    "Data Science",
    "Cloud Infrastructure"
  ],
  "declining_categories": [
    "Quality Assurance",
    "Technical Support",
    "Project Management"
  ],
  "confidence": 75,
  "insights": [
    "The market is showing a clear upward trend, with the current total (1009) consistently outperforming the 30-day average (982), signaling a recovery phase.",
    "Unicorn and FAANG+ tiers remain stable, suggesting that hiring volume is being driven by sustained demand from established tech entities rather than speculative growth.",
    "The 7-day average (1001) is trending higher than the 30-day average, indicating that momentum is accelerating as we move into the next month."
  ],
  "generated_at": "2026-04-13T01:16:09.823885",
  "data_points": 40,
  "date_range": {
    "start": "2026-03-05",
    "end": "2026-04-13"
  }
}